maas_backend_client/__init__.py
maas_backend_client/api/__init__.py
maas_backend_client/api/data_sets/__init__.py
maas_backend_client/api/data_sets/data_set_create_api_v1_data_sets_post.py
maas_backend_client/api/data_sets/data_set_delete_api_v1_data_sets_data_set_id_delete.py
maas_backend_client/api/data_sets/data_set_detail_api_v1_data_sets_data_set_id_get.py
maas_backend_client/api/data_sets/data_set_list_api_v1_data_sets_list_post.py
maas_backend_client/api/data_sets/data_set_template_api_v1_data_sets_download_template_post.py
maas_backend_client/api/data_sets/data_set_type_list_api_v1_data_sets_type_list_get.py
maas_backend_client/api/data_sets/data_set_version_count_api_v1_data_sets_data_set_id_version_count_get.py
maas_backend_client/api/data_sets/data_set_version_create_api_v1_data_sets_data_set_id_version_post.py
maas_backend_client/api/data_sets/data_set_version_delete_api_v1_data_sets_versions_version_id_delete.py
maas_backend_client/api/data_sets/data_set_version_line_create_api_v1_data_sets_versions_version_id_line_post.py
maas_backend_client/api/data_sets/data_set_version_line_delete_api_v1_data_sets_versions_line_line_id_delete.py
maas_backend_client/api/data_sets/data_set_version_line_list_api_v1_data_sets_versions_version_id_line_list_post.py
maas_backend_client/api/data_sets/data_set_version_line_update_api_v1_data_sets_versions_line_line_id_put.py
maas_backend_client/api/data_sets/data_set_version_update_api_v1_data_sets_versions_version_id_put.py
maas_backend_client/api/data_sets/export_task_progress_api_v1_data_sets_export_tasks_task_id_get.py
maas_backend_client/api/data_sets/export_version_api_v1_data_sets_versions_version_id_export_get.py
maas_backend_client/api/data_sets/list_file_detail_api_v1_data_sets_versions_version_id_file_detail_post.py
maas_backend_client/api/default/__init__.py
maas_backend_client/api/default/root_get.py
maas_backend_client/api/files/__init__.py
maas_backend_client-0.1.2.dist-info/WHEEL
maas_backend_client-0.1.2.dist-info/METADATA
maas_backend_client-0.1.2.dist-info/RECORD
