Metadata-Version: 2.3
Name: maas-backend-client
Version: 0.1.2
Summary: A client library for accessing Maas Backend
Requires-Dist: httpx>=0.23.0,<0.29.0
Requires-Dist: attrs>=22.2.0
Requires-Dist: python-dateutil>=2.8.0,<3
Requires-Python: ~=3.9
